LICENSE
README.md
setup.cfg
setup.py
stainaug/__init__.py
stainaug/augment.py
stainaug.egg-info/PKG-INFO
stainaug.egg-info/SOURCES.txt
stainaug.egg-info/dependency_links.txt
stainaug.egg-info/requires.txt
stainaug.egg-info/top_level.txt
stainaug/augmenters/__init__.py
stainaug/augmenters/augmenterbase.py
stainaug/augmenters/color/__init__.py
stainaug/augmenters/color/coloraugmenterbase.py
stainaug/augmenters/color/hedcoloraugmenter.py
stainaug/augmenters/color/utils/__init__.py
stainaug/augmenters/color/utils/custom_hed_transform.py