Metadata-Version: 2.1
Name: stainaug
Version: 0.0.2
Summary: A tool for H&E image augmentation
Home-page: https://github.com/estorrs/stainaug
Author: Erik Storrs
Author-email: estorrs@gmail.com
License: UNKNOWN
Keywords: H&E stain augmentation
Platform: UNKNOWN
Classifier: License :: OSI Approved :: MIT License
Classifier: Programming Language :: Python :: 3.6
Classifier: Programming Language :: Python :: 3.7
Classifier: Programming Language :: Python :: 3.8
Classifier: Programming Language :: Python :: 3.9
Requires-Python: >=3.6
License-File: LICENSE
